aioapp/__init__.py
aioapp/app.py
aioapp/config.py
aioapp/error.py
aioapp/misc.py
aioapp/tracer.py
tests/__init__.py
tests/conftest.py
tests/test_app.py
tests/test_config.py
tests/test_misc.py
tests/test_tracer.py
aioapp-0.0.2b8.dist-info/AUTHORS.rst
aioapp-0.0.2b8.dist-info/LICENSE
aioapp-0.0.2b8.dist-info/METADATA
aioapp-0.0.2b8.dist-info/WHEEL
aioapp-0.0.2b8.dist-info/top_level.txt
aioapp-0.0.2b8.dist-info/RECORD
