Metadata-Version: 2.1
Name: aioapp
Version: 0.0.2b8
Summary: Micro framework based on asyncio
Home-page: https://github.com/inplat/aioapp
Author: Konstantin Stepanov
Author-email: UNKNOWN
License: Apache License 2.0
Keywords: aioapp
Platform: UNKNOWN
Classifier: Development Status :: 2 - Pre-Alpha
Classifier: Intended Audience :: Developers
Classifier: License :: OSI Approved :: Apache Software License
Classifier: Natural Language :: English
Classifier: Programming Language :: Python :: 3
Classifier: Programming Language :: Python :: 3.6
Requires-Dist: attrs (==18.2.0)
Requires-Dist: yarl (==1.2.6)
Requires-Dist: aiozipkin (==0.4.0)
